roma_data/__init__.py
roma_data/__main__.py
roma_data/cli.py
roma_data/config.py
roma_data/constants.py
roma_data/pipeline.py
roma_data/export/__init__.py
roma_data/export/csv.py
roma_data/export/geojson.py
roma_data/export/sqlite.py
roma_data/sources/__init__.py
roma_data/sources/awmc.py
roma_data/sources/base.py
roma_data/sources/itinere.py
roma_data/sources/orbis.py
roma_data/sources/pleiades.py
roma_data/sources/topostext.py
roma_data/sources/wikidata.py
roma_data/spatial/__init__.py
roma_data/spatial/index.py
roma_data/transform/__init__.py
roma_data/transform/enrichment.py
roma_data/transform/events.py
roma_data/transform/locations.py
roma_data/transform/people.py
roma_data/transform/provinces.py
roma_data/transform/roads.py
roma_data/validation/__init__.py
roma_data/validation/checks.py
roma_data_pipeline-0.1.1.dist-info/METADATA
roma_data_pipeline-0.1.1.dist-info/WHEEL
roma_data_pipeline-0.1.1.dist-info/entry_points.txt
roma_data_pipeline-0.1.1.dist-info/licenses/LICENSE
roma_data_pipeline-0.1.1.dist-info/licenses/LICENSE-DATA
roma_data_pipeline-0.1.1.dist-info/RECORD
