Metadata-Version: 2.4
Name: roma-data-pipeline
Version: 0.1.1
Summary: Comprehensive ETL pipeline for Roman world data from Pleiades, ORBIS, Wikidata, and more
Project-URL: Homepage, https://github.com/thomaspalaio/roma-data-pipeline
Project-URL: Documentation, https://github.com/thomaspalaio/roma-data-pipeline#readme
Project-URL: Repository, https://github.com/thomaspalaio/roma-data-pipeline
Project-URL: Issues, https://github.com/thomaspalaio/roma-data-pipeline/issues
Author: Thomas Palaio
License-Expression: MIT
License-File: LICENSE
License-File: LICENSE-DATA
Keywords: ancient-geography,digital-humanities,etl,geospatial,linked-data,orbis,pleiades,roman-history
Classifier: Development Status :: 4 - Beta
Classifier: Environment :: Console
Classifier: Intended Audience :: Developers
Classifier: Intended Audience :: Science/Research
Classifier: License :: OSI Approved :: MIT License
Classifier: Operating System :: OS Independent
Classifier: Programming Language :: Python :: 3
Classifier: Programming Language :: Python :: 3.9
Classifier: Programming Language :: Python :: 3.10
Classifier: Programming Language :: Python :: 3.11
Classifier: Programming Language :: Python :: 3.12
Classifier: Topic :: Database
Classifier: Topic :: Scientific/Engineering :: GIS
Classifier: Typing :: Typed
Requires-Python: >=3.9
Requires-Dist: click>=8.0
Requires-Dist: geopandas>=0.14
Requires-Dist: pandas>=2.0
Requires-Dist: requests>=2.28
Requires-Dist: rich>=13.0
Requires-Dist: shapely>=2.0
Requires-Dist: sparqlwrapper>=2.0
Requires-Dist: tqdm>=4.64
Provides-Extra: dev
Requires-Dist: mypy>=1.0; extra == 'dev'
Requires-Dist: pre-commit>=3.0; extra == 'dev'
Requires-Dist: pytest-cov>=4.0; extra == 'dev'
Requires-Dist: pytest>=7.0; extra == 'dev'
Requires-Dist: ruff>=0.1; extra == 'dev'
Provides-Extra: docs
Requires-Dist: mkdocs-material>=9.0; extra == 'docs'
Requires-Dist: mkdocs>=1.5; extra == 'docs'
Requires-Dist: mkdocstrings[python]>=0.24; extra == 'docs'
